llm_async/__init__.py
llm_async/models/__init__.py
llm_async/models/event.py
llm_async/models/message.py
llm_async/models/response.py
llm_async/models/tool_call.py
llm_async/providers/__init__.py
llm_async/providers/base.py
llm_async/providers/claude.py
llm_async/providers/google.py
llm_async/providers/openai.py
llm_async/providers/openai_responses.py
llm_async/providers/openrouter.py
llm_async/utils/__init__.py
llm_async/utils/http.py
llm_async/utils/retry.py
llm_async-0.3.1.dist-info/METADATA
llm_async-0.3.1.dist-info/WHEEL
llm_async-0.3.1.dist-info/RECORD
