Metadata-Version: 2.1
Name: llm_async
Version: 0.3.1
Summary: Multi-LLM Provider Library
Home-page: https://github.com/sonic182/llm-async
License: MIT
Keywords: llm,asyncio,ai,openai,anthropic,claude,gemini,google,openrouter,streaming,tool calling,json schema,structured outputs,python,aiosonic
Author: Johanderson Mogollon
Author-email: johander1822@gmail.com
Requires-Python: >=3.10,<4.0
Classifier: Intended Audience :: Developers
Classifier: License :: OSI Approved :: MIT License
Classifier: Programming Language :: Python :: 3
Classifier: Programming Language :: Python :: 3.10
Classifier: Programming Language :: Python :: 3.11
Classifier: Programming Language :: Python :: 3.12
Classifier: Programming Language :: Python :: 3 :: Only
Classifier: Topic :: Scientific/Engineering :: Artificial Intelligence
Classifier: Topic :: Software Development :: Libraries
Requires-Dist: aiosonic
Project-URL: Bug Tracker, https://github.com/sonic182/llm-async/issues
Project-URL: Changelog, https://github.com/sonic182/llm-async/blob/main/CHANGELOG.md
Project-URL: Documentation, https://github.com/sonic182/llm-async#readme
Project-URL: Repository, https://github.com/sonic182/llm-async
Project-URL: Source, https://github.com/sonic182/llm-async
